{
    "footer": {
        "text": "Character Guide \u2022 Synergy: Electro Traveler | Update Date: 09/28/2022 | Editor: Samantha#9907"
    },
    "thumbnail": {
        "url": "https://i.imgur.com/B0zBZMi.png"
    },
    "fields": [],
    "color": 11104511,
    "type": "rich",
    "description": "eula,fischl,diona,electrotraveler|yoimiya,beidou,electrotraveler,xingqiu|childe,beidou,electrotraveler,bennett|tighnari,yaemiko,electrotraveler,sayu|collei,tighnari,electrotraveler,jean|electrotraveler,yanfei,venti,bennett",
    "title": "Electro Traveler | Team Composition and Synergy"
}