{
    "footer": {
        "text": "Character Guide \u2022 Build: Collei | Update Date: 08/26/2022 | Editor: Luno#1337"
    },
    "thumbnail": {
        "url": "https://api.ambr.top/assets/UI/UI_AvatarIcon_Collei.png"
    },
    "fields": [
        {
            "inline": "true",
            "name": "Best Weapon(s):",
            "value": "__Elegy of the End__\nGenerally Collei\u2019s best weapon, for its buffing capabilities and large Energy Recharge stat, complimenting both Collei herself as well as her teammates.\n\n__Favonius Warbow__\nStrong F2P option that supplies a large amount of Energy Recharge stats. Additionally, the particles generated by the weapon passive further lowers Collei\u2019s, as well as her teammates Energy Requirements.\n** **"
        },
        {
            "inline": "true",
            "name": "Replacement Weapon:",
            "value": "__The Stringless__\nFocuses on Collei\u2019s personal damage by providing Elemental Mastery for her Spreads and DMG% bonuses to her main sources of damage \u2014 which also benefits her Spreads.\n\n__Sacrificial Bow__\nWhen Collei is paired with a second Dendro, Sacrificial Bow can be utilized to generate more dendro particles \u2014 effectively lowering both Dendro\u2019s ER requirements significantly.\n** **"
        },
        {
            "inline": "false",
            "name": "Best Artifact Set:",
            "value": "x4-deepwoodmemories"
        },
        {
            "inline": "false",
            "name": "Second Best Artifact Set:",
            "value": "x4-noblesseoblige"
        },
        {
            "inline": "false",
            "name": "Third Best Artifact Set:",
            "value": "x4-tenacityofthemillelith"
        },
        {
            "inline": "true",
            "name": "Main Stats Priority",
            "value": "<sands> Energy Recharge OR Elemental Mastery OR ATK % |<goblet> Dendro DMG Bonus OR Elemental Mastery |<circlet> CRIT Rate or DMG"
        },
        {
            "inline": "true",
            "name": "Substats Priority",
            "value": "Energy Recharge ( requirements vary based on team, check with the ERC )|CRIT Rate|CRIT DMG|Elemental Mastery|ATK %"
        },
        {
            "inline": "false",
            "name": "Talent Priority",
            "value": "**1)** Burst\n**2)** Skill\nAuto attacks may be left unlevelled.\n"
        },
        {
            "inline": "false",
            "name": "Notes:",
            "value": "Elemental Mastery goblet can be utilized should players not have a Dendro DMG Bonus goblet. "
        }
    ],
    "color": 6794623,
    "type": "rich",
    "title": "Collei (Speculation Build) | Build"
}