[
    {
        "footer": {
            "text": "Character Guide • Build: Traveler | Update Date: 10/21/2023 | Editor: ._.samantha._."
        },
        "thumbnail": {
            "url": "https://gi.yatta.moe/assets/UI/UI_AvatarIcon_PlayerBoy.png"
        },
        "fields": [
            {
                "inline": "true",
                "name": "Best Weapon(s):",
                "value": "__Favonius Sword, Sacrificial Sword__\nTraveler is a capable off field Dendro applier, however Traveler generates little energy for themselves, therefore weapons with an Energy Recharge substat is ideal to ensure that Traveler is capable of maintaining uptime on their Elemental Burst. Favonius Sword has the added benefit of being able to restore energy for the entire team"
            },
            {
                "inline": "true",
                "name": "Replacement Weapon(s):",
                "value": "__Freedom Sworn, Iron Sting__\nThis weapon enhances Traveler's damage if used in a Spread team. Freedom Sworn has the added benefit of being able to buff the entire team as well.\n__Fleuve Cendre Ferrymen__\nBaseline for free options, with Energy Recharge and a buff for Energy Recharge.\n__Wolf Fang__\nBattle Pass weapon that's good for their personal damage."
            },
            {
                "inline": "false",
                "name": "Best Artifact Set:",
                "value": "15025"
            },
            {
                "inline": "false",
                "name": "Second Best Artifact Set:",
                "value": "15007"
            },
            {
                "inline": "false",
                "name": "Third Best Artifact Set:",
                "value": "15020"
            },
            {
                "inline": "true",
                "name": "Main Stats Priority",
                "value": "<sands> Energy Recharge or Elemental Mastery or ATK% |<goblet> Dendro DMG or Elemental Mastery or ATK% |<circlet> CRIT Rate or CRIT DMG"
            },
            {
                "inline": "true",
                "name": "Substats Priority",
                "value": "Energy Recharge(till requirements)|CRIT Rate|CRIT DMG|Elemental Mastery"
            },
            {
                "inline": "false",
                "name": "Talent Priority",
                "value": "**1)** Elemental Burst: Surgent Manifestation\n**2)** Elemental Skill: Razorgrass Blade\n**N/A)**Normal Attack: Foreign Fieldcleaver"
            },
            {
                "inline": "false",
                "name": "Notes:",
                "value": "Note: Traveler's Energy requirements vary a lot by team, use an energy recharge calculator to calculate Traveler's Energy requirements for your team."
            }
        ],
        "flags": 0,
        "color": 5494962,
        "type": "rich",
        "title": "Dendro Traveler (Off-Field DPS) | Build"
    }
]