{
    "footer": {
        "text": "Character Guide • Passive Talents: Traveler"
    },
    "thumbnail": {
        "url": "https://i.imgur.com/B0zBZMi.png"
    },
    "fields": [
        {
            "inline": false,
            "name": "> Thunderflash",
            "value": "When another nearby character in the party obtains an Abundance Amulet created by Lightning Blade, Lightning Blade's CD is decreased by 1.5s.\n*Unlocked at Ascension 1*"
        },
        {
            "inline": false,
            "name": "> Resounding Roar",
            "value": "Increases the Energy Recharge effect granted by Lightning Blade's Abundance Amulet by 10% of the Traveler's Energy Recharge.\n*Unlocked at Ascension 4*"
        }
    ],
    "color": 11104511,
    "type": "rich",
    "title": "Traveler | Passive Talents"
}