{
    "thumbnail": {
        "url": "https://i.imgur.com/Tr5VWv6.png"
    },
    "fields": [
        {
            "inline": false,
            "name": "Best Weapon:",
            "value": "Black Tassel"
        },
        {
            "inline": false,
            "name": "Replacement Weapon:",
            "value": "Skyward Spine, Favonius Lance, The Catch (R5), Black Tassel"
        },
        {
            "inline": false,
            "name": "Best Artifact Set:",
            "value": "\n*Instructor <:4x:957694032216215573>*\n\u2022 Increases Elemental Mastery by 80.\n\u2022 Upon triggering an Elemental Reaction, increases all party members' Elemental Mastery by 120 for 8s.\n        "
        },
        {
            "inline": false,
            "name": "Second Best Artifact Set:",
            "value": "\n*Noblesse Oblige <:4x:957694032216215573>*\n• Elemental Burst DMG +20%.\n• Using an Elemental Burst increases all party members' ATK by 20% for 12s. This effect cannot stack.\n        "
        },
        {
            "inline": false,
            "name": "Third Best Artifact Set:",
            "value": "\n*Tenacity of the Millelith <:2x:957694031343812619>\nNoblesse Oblige <:2x:957694031343812619>*\n\u2022 HP +20%\n\u2022 Elemental Burst DMG +20%.\n        "
        },
        {
            "inline": true,
            "name": "Stat Priority",
            "value": "\n**Main Stats**\n<:sandsofeon:957412516038844486> HP % / Energy Recharge\n<:gobletofeonothem:957412513958477864> HP %\n<:circletoflogos:957412513820053594> HP % / Crit Rate\n**Substats**\n・Energy Recharge\n・HP %\n・Crit Rate\n        "
        },
        {
            "inline": true,
            "name": "Talent Priority:",
            "value": "\n**1)** Elemental Skill: Blazing Blessing\n**2)** Elemental Burst: Imbricated Armor\n**3)** Normal Attack: Swiftshatter Spear\n        "
        },
        {
            "inline": false,
            "name": "Notes:",
            "value": "Thoma would want some Crit Rate Sub Stats, if you are running Favonius Lance, to trigger its passive."
        }
    ],
    "color": 16733525,
    "type": "rich",
    "title": "Thoma (Support) | Build",
    "footer": {
        "text": "Character Guide • Build: Thoma"
    }
}