{
    "footer": {
        "text": "Character Guide • Introduction: Xiao"
    },
    "image": {
        "url": "http://cdn.genshinwizard.com/7/02a10edbdb/anemo.png"
    },
    "thumbnail": {
        "url": "https://i.imgur.com/uSkv5pg.png"
    },
    "fields": [
        {
            "inline": true,
            "name": "Nation",
            "value": "Liyue"
        },
        {
            "inline": true,
            "name": "Affiliation",
            "value": "Liyue Adeptus"
        },
        {
            "inline": true,
            "name": "Element Type",
            "value": "Anemo <:Anemo:951729013859155979>"
        },
        {
            "inline": true,
            "name": "Rarity",
            "value": "★★★★★"
        },
        {
            "inline": true,
            "name": "Constellation",
            "value": "Alatus Nemeseos"
        },
        {
            "inline": true,
            "name": "Weapon",
            "value": "<:Skill_A_03:1063905224651190462> Polearm:Skill_A_03:1063905224651190462>"
        }
    ],
    "color": 5494962,
    "type": "rich",
    "description": "A yaksha adeptus that defends Liyue. Also heralded as the \"Conqueror of Demons\" and \"Vigilant Yaksha.\"",
    "title": "Xiao | Introduction"
}